[
  {
    "season_title": "موسم 1",
    "season": [
      {
        "video_title": "موسم 1 الحلقة 1",
        "video_download": "",
        "server_translator": [
          {
            "server_title": "سيرفر 1",
            "server_link": "<iframe allowfullscreen='true' webkitallowfullscreen='true' mozallowfullscreen='true' width='100%' height='100%' src='https://esheeq.net/emb?serv=8863948' frameborder='0' allow='autoplay'></iframe>"
          },
          {
            "server_title": "سيرفر 2",
            "server_link": "<iframe allowfullscreen='true' webkitallowfullscreen='true' mozallowfullscreen='true' width='100%' height='100%' src='https://arabveturk.com/embed-elxpn5mos28r.html' frameborder='0' allow='autoplay'></iframe>"
          },
          {
            "server_title": "سيرفر 3",
            "server_link": "<iframe allowfullscreen='true' webkitallowfullscreen='true' mozallowfullscreen='true' width='100%' height='100%' src='https://www.ok.ru/videoembed/31213357730' frameborder='0' allow='autoplay'></iframe>"
          }
        ]
      },
      {
        "video_title": "موسم 1 الحلقة 2",
        "video_download": "",
        "server_translator": [
          {
            "server_title": "سيرفر 1",
            "server_link": "<iframe allowfullscreen='true' webkitallowfullscreen='true' mozallowfullscreen='true' width='100%' height='100%' src='https://esheeq.net/emb?serv=8863949' frameborder='0' allow='autoplay'></iframe>"
          },
          {
            "server_title": "سيرفر 2",
            "server_link": "<iframe allowfullscreen='true' webkitallowfullscreen='true' mozallowfullscreen='true' width='100%' height='100%' src='https://arabveturk.com/embed-kz18uh2r38el.html' frameborder='0' allow='autoplay'></iframe>"
          },
          {
            "server_title": "سيرفر 3",
            "server_link": "<iframe allowfullscreen='true' webkitallowfullscreen='true' mozallowfullscreen='true' width='100%' height='100%' src='https://www.ok.ru/videoembed/31921146530' frameborder='0' allow='autoplay'></iframe>"
          }
        ]
      },
      {
        "video_title": "موسم 1 الحلقة 3",
        "video_download": "",
        "server_translator": [
          {
            "server_title": "سيرفر 1",
            "server_link": "<iframe allowfullscreen='true' webkitallowfullscreen='true' mozallowfullscreen='true' width='100%' height='100%' src='https://esheeq.net/emb?serv=8863950' frameborder='0' allow='autoplay'></iframe>"
          },
          {
            "server_title": "سيرفر 2",
            "server_link": "<iframe allowfullscreen='true' webkitallowfullscreen='true' mozallowfullscreen='true' width='100%' height='100%' src='https://arabveturk.com/embed-tfvwhrqrwj6h.html' frameborder='0' allow='autoplay'></iframe>"
          },
          {
            "server_title": "سيرفر 3",
            "server_link": "<iframe allowfullscreen='true' webkitallowfullscreen='true' mozallowfullscreen='true' width='100%' height='100%' src='https://www.ok.ru/videoembed/32413387426' frameborder='0' allow='autoplay'></iframe>"
          }
        ]
      },
      {
        "video_title": "موسم 1 الحلقة 4",
        "video_download": "",
        "server_translator": [
          {
            "server_title": "سيرفر 1",
            "server_link": "<iframe allowfullscreen='true' webkitallowfullscreen='true' mozallowfullscreen='true' width='100%' height='100%' src='https://esheeq.net/emb?serv=8863951' frameborder='0' allow='autoplay'></iframe>"
          },
          {
            "server_title": "سيرفر 2",
            "server_link": "<iframe allowfullscreen='true' webkitallowfullscreen='true' mozallowfullscreen='true' width='100%' height='100%' src='https://arabveturk.com/embed-smhezmk2t4ve.html' frameborder='0' allow='autoplay'></iframe>"
          },
          {
            "server_title": "سيرفر 3",
            "server_link": "<iframe allowfullscreen='true' webkitallowfullscreen='true' mozallowfullscreen='true' width='100%' height='100%' src='https://www.ok.ru/videoembed/32775211682' frameborder='0' allow='autoplay'></iframe>"
          }
        ]
      },
      {
        "video_title": "موسم 1 الحلقة 5",
        "video_download": "",
        "server_translator": [
          {
            "server_title": "سيرفر 1",
            "server_link": "<iframe allowfullscreen='true' webkitallowfullscreen='true' mozallowfullscreen='true' width='100%' height='100%' src='https://esheeq.net/emb?serv=8863952' frameborder='0' allow='autoplay'></iframe>"
          },
          {
            "server_title": "سيرفر 2",
            "server_link": "<iframe allowfullscreen='true' webkitallowfullscreen='true' mozallowfullscreen='true' width='100%' height='100%' src='https://arabveturk.com/embed-on5btbx32l9q.html' frameborder='0' allow='autoplay'></iframe>"
          },
          {
            "server_title": "سيرفر 3",
            "server_link": "<iframe allowfullscreen='true' webkitallowfullscreen='true' mozallowfullscreen='true' width='100%' height='100%' src='https://www.ok.ru/videoembed/32984533666' frameborder='0' allow='autoplay'></iframe>"
          }
        ]
      },
      {
        "video_title": "موسم 1 الحلقة 6",
        "video_download": "",
        "server_translator": [
          {
            "server_title": "سيرفر 1",
            "server_link": "<iframe allowfullscreen='true' webkitallowfullscreen='true' mozallowfullscreen='true' width='100%' height='100%' src='https://esheeq.net/emb?serv=8863953' frameborder='0' allow='autoplay'></iframe>"
          },
          {
            "server_title": "سيرفر 2",
            "server_link": "<iframe allowfullscreen='true' webkitallowfullscreen='true' mozallowfullscreen='true' width='100%' height='100%' src='https://arabveturk.com/embed-h1onddzgjmrf.html' frameborder='0' allow='autoplay'></iframe>"
          },
          {
            "server_title": "سيرفر 3",
            "server_link": "<iframe allowfullscreen='true' webkitallowfullscreen='true' mozallowfullscreen='true' width='100%' height='100%' src='https://www.ok.ru/videoembed/33275185826' frameborder='0' allow='autoplay'></iframe>"
          }
        ]
      },
      {
        "video_title": "موسم 1 الحلقة 7",
        "video_download": "",
        "server_translator": [
          {
            "server_title": "سيرفر 1",
            "server_link": "<iframe allowfullscreen='true' webkitallowfullscreen='true' mozallowfullscreen='true' width='100%' height='100%' src='https://esheeq.net/emb?serv=8863954' frameborder='0' allow='autoplay'></iframe>"
          },
          {
            "server_title": "سيرفر 2",
            "server_link": "<iframe allowfullscreen='true' webkitallowfullscreen='true' mozallowfullscreen='true' width='100%' height='100%' src='https://arabveturk.com/embed-hsys2g4jjz0g.html' frameborder='0' allow='autoplay'></iframe>"
          },
          {
            "server_title": "سيرفر 3",
            "server_link": "<iframe allowfullscreen='true' webkitallowfullscreen='true' mozallowfullscreen='true' width='100%' height='100%' src='https://www.ok.ru/videoembed/32690408009' frameborder='0' allow='autoplay'></iframe>"
          }
        ]
      },
      {
        "video_title": "موسم 1 الحلقة 8",
        "video_download": "",
        "server_translator": [
          {
            "server_title": "سيرفر 1",
            "server_link": "<iframe allowfullscreen='true' webkitallowfullscreen='true' mozallowfullscreen='true' width='100%' height='100%' src='https://esheeq.net/emb?serv=8863955' frameborder='0' allow='autoplay'></iframe>"
          },
          {
            "server_title": "سيرفر 2",
            "server_link": "<iframe allowfullscreen='true' webkitallowfullscreen='true' mozallowfullscreen='true' width='100%' height='100%' src='https://arabveturk.com/embed-7pyuf6776iy5.html' frameborder='0' allow='autoplay'></iframe>"
          }
        ]
      },
      {
        "video_title": "موسم 1 الحلقة 9",
        "video_download": "",
        "server_translator": [
          {
            "server_title": "سيرفر 1",
            "server_link": "<iframe allowfullscreen='true' webkitallowfullscreen='true' mozallowfullscreen='true' width='100%' height='100%' src='https://esheeq.net/emb?serv=8863956' frameborder='0' allow='autoplay'></iframe>"
          },
          {
            "server_title": "سيرفر 2",
            "server_link": "<iframe allowfullscreen='true' webkitallowfullscreen='true' mozallowfullscreen='true' width='100%' height='100%' src='https://arabveturk.com/embed-pw1kv1u9oumv.html' frameborder='0' allow='autoplay'></iframe>"
          }
        ]
      }
    ]
  }
]
